README.txt
setup.py
tests/__init__.py
zclient/__init__.py
zclient/options.py
zclient/settings.py
zclient/version.py
zclient.egg-info/PKG-INFO
zclient.egg-info/SOURCES.txt
zclient.egg-info/dependency_links.txt
zclient.egg-info/entry_points.txt
zclient.egg-info/top_level.txt
zclient/bin/__init__.py
zclient/bin/run.py
zclient/zenoss/__init__.py
zclient/zenoss/api.py
zclient/zenoss/filters.py