Metadata-Version: 1.0
Name: zclient
Version: 0.0.4
Summary: A simple client that can communicate with a Zenoss server.
Home-page: http://http://pypi.python.org/pypi/zclient
Author: Jestin Woods
Author-email: jestin.woods@gmail.com
License: BSD
Keywords: zclient documentation
Platform: UNKNOWN
Classifier: Development Status :: 3 - Alpha
Classifier: Topic :: Utilities
Classifier: License :: OSI Approved :: BSD License
